anyio_typer/__init__.py
anyio_typer/py.typed
anyio_typer-0.0.0.dist-info/licenses/LICENSE
anyio_typer-0.0.0.dist-info/METADATA
anyio_typer-0.0.0.dist-info/WHEEL
anyio_typer-0.0.0.dist-info/top_level.txt
anyio_typer-0.0.0.dist-info/RECORD
