Metadata-Version: 2.4
Name: anyio-typer
Version: 0.0.0
Summary: Combines anyio and typer together for writing asynchronous commandlines
Author-email: Vizonex <VizonexBusiness@gmail.com>
Requires-Python: >=3.9
License-File: LICENSE
Requires-Dist: typer>=0.16.0
Requires-Dist: anyio>=4.10.0
Provides-Extra: trio
Requires-Dist: trio>=0.30.0; extra == "trio"
Provides-Extra: uvloop
Requires-Dist: uvloop>=0.21.0; sys_platform != "win32" and extra == "uvloop"
Requires-Dist: winloop>=0.2.2; sys_platform == "win32" and extra == "uvloop"
Dynamic: license-file
